liom_toolkit/__init__.py
liom_toolkit/conversion/__init__.py
liom_toolkit/conversion/conversion.py
liom_toolkit/registration/__init__.py
liom_toolkit/registration/register.py
liom_toolkit/registration/templating.py
liom_toolkit/segmentation/__init__.py
liom_toolkit/segmentation/plane_segmentation.py
liom_toolkit/segmentation/stats.py
liom_toolkit/segmentation/volume_segmentation.py
liom_toolkit/segmentation/vseg/__init__.py
liom_toolkit/segmentation/vseg/cldice.py
liom_toolkit/segmentation/vseg/dataset.py
liom_toolkit/segmentation/vseg/loss.py
liom_toolkit/segmentation/vseg/model.py
liom_toolkit/segmentation/vseg/prediction.py
liom_toolkit/segmentation/vseg/training.py
liom_toolkit/segmentation/vseg/utils.py
liom_toolkit/segmentation/vseg/validation.py
liom_toolkit/utils/__init__.py
liom_toolkit/utils/allen_sdk.py
liom_toolkit/utils/dask_client.py
liom_toolkit/utils/io.py
liom_toolkit/utils/utils.py
liom_toolkit/visualization/__init__.py
liom_toolkit/visualization/slice_extraction.py
liom_toolkit-0.8.19.dist-info/LICENSE
liom_toolkit-0.8.19.dist-info/METADATA
liom_toolkit-0.8.19.dist-info/WHEEL
liom_toolkit-0.8.19.dist-info/top_level.txt
liom_toolkit-0.8.19.dist-info/RECORD
