Metadata-Version: 2.1
Name: liom-toolkit
Version: 0.8.19
Summary: Package to support the research of LIOM.
Home-page: https://github.com/LIOMLab/liom-toolkit
Author: Laboratoire d’Imagerie Optique et Moléculaire
Author-email: frederic.lesage@polymtl.ca
License: GPLv3+
Requires-Python: >=3.10
License-File: LICENSE
Requires-Dist: antspyx>=0.5.3
Requires-Dist: tqdm
Requires-Dist: scikit-image
Requires-Dist: ome-zarr>=0.9.0
Requires-Dist: nibabel
Requires-Dist: zarr
Requires-Dist: h5py
Requires-Dist: pynrrd
Requires-Dist: PyWavelets
Requires-Dist: SimpleITK
Requires-Dist: allensdk
Requires-Dist: dask
Requires-Dist: opencv-python
Requires-Dist: torch
Requires-Dist: torchvision
Requires-Dist: wandb
Requires-Dist: patchify
Requires-Dist: natsort
Requires-Dist: ruamel.yaml==0.16.10
